labda_parsers/__init__.py
labda_parsers/actigraph.py
labda_parsers/axivity.py
labda_parsers/parser.py
labda_parsers/py.typed
labda_parsers/sens/__init__.py
labda_parsers/sens/file.py
labda_parsers-0.1.0.dist-info/METADATA
labda_parsers-0.1.0.dist-info/WHEEL
labda_parsers-0.1.0.dist-info/licenses/LICENSE
labda_parsers-0.1.0.dist-info/RECORD
